[{"text":"When the sky bursts open,","foot_notes":{}},{"text":"obeying its Lord as it must,","foot_notes":{}},{"text":"and when the earth is flattened out,","foot_notes":{}},{"text":"and ejects ˹all˺ its contents <sup foot_note=1295>1295</sup> and becomes empty,","foot_notes":{"1295":"i.e., treasures and dead bodies."}},{"text":"obeying its Lord as it must, ˹surely you will all be judged˺.","foot_notes":{}},{"text":"O humanity! Indeed, you are labouring restlessly towards your Lord, and will ˹eventually˺ meet the consequences.","foot_notes":{}},{"text":"As for those who are given their record in their right hand,","foot_notes":{}},{"text":"they will have an easy reckoning,","foot_notes":{}},{"text":"and will return to their people joyfully.","foot_notes":{}},{"text":"And as for those who are given their record ˹in their left hand˺ from behind their backs,","foot_notes":{}},{"text":"they will cry for ˹instant˺ destruction,","foot_notes":{}},{"text":"and will burn in the blazing Fire.","foot_notes":{}},{"text":"For they used to be prideful among their people,","foot_notes":{}},{"text":"thinking they would never return ˹to Allah˺.","foot_notes":{}},{"text":"Yes ˹they would˺! Surely their Lord has always been All-Seeing of them.","foot_notes":{}},{"text":"So, I do swear by the twilight!","foot_notes":{}},{"text":"And by the night and whatever it envelops!","foot_notes":{}},{"text":"And by the moon when it waxes full!","foot_notes":{}},{"text":"You will certainly pass from one state to another. <sup foot_note=1296>1296</sup>","foot_notes":{"1296":"You will pass from life to death and from death to resurrection, from well-being to sickness and from sickness to well-being, from poverty to richness and from richness to poverty, etc."}},{"text":"So what is the matter with them that they do not believe,","foot_notes":{}},{"text":"and when the Quran is recited to them, they do not bow down ˹in submission˺? <sup foot_note=1297>1297</sup>","foot_notes":{"1297":"lit., they do not prostrate."}},{"text":"In fact, the disbelievers persist in denial.","foot_notes":{}},{"text":"But Allah knows best whatever they hide.","foot_notes":{}},{"text":"So give them good news of a painful punishment.","foot_notes":{}},{"text":"But those who believe and do good will have a never-ending reward.","foot_notes":{}}]
